gato/__init__.py
gato/entity.py
gato/generator.py
gato/llm.py
gato/prompt.py
gato/service.py
gato/.config/action-system-message.txt
gato/.config/scenario-system-messages.txt
gato/.config/scenario-params/categories.txt
gato/.config/scenario-params/domains.txt
gato/.config/scenario-params/entropies.txt
gato/.config/scenario-params/regions.txt
gato/.config/scenario-params/scopes.txt
gato/.config/scenario-params/severities.txt
gato_toolkit-0.3.1.dist-info/LICENSE
gato_toolkit-0.3.1.dist-info/METADATA
gato_toolkit-0.3.1.dist-info/WHEEL
gato_toolkit-0.3.1.dist-info/top_level.txt
gato_toolkit-0.3.1.dist-info/RECORD
