Metadata-Version: 2.1
Name: gato-toolkit
Version: 0.3.1
Summary: A toolkit for furthering research on AI alignment.
Home-page: https://github.com/FyZyX/gato-toolkit
Author: Lucas Lofaro <lucasmlofaro@gmail.com>
License: MIT
Classifier: Development Status :: 2 - Pre-Alpha
Classifier: License :: OSI Approved :: MIT License
Classifier: Programming Language :: Python :: 3
Classifier: Programming Language :: Python :: 3.10
License-File: LICENSE
Requires-Dist: openai (>=0.27.6)
Requires-Dist: pydantic (>=1.10.7)
